kiro_process_manager/__init__.py
kiro_process_manager/cli.py
kiro_process_manager/manager.py
kiro_process_manager-1.1.2.dist-info/licenses/LICENSE
kiro_process_manager-1.1.2.dist-info/METADATA
kiro_process_manager-1.1.2.dist-info/WHEEL
kiro_process_manager-1.1.2.dist-info/entry_points.txt
kiro_process_manager-1.1.2.dist-info/top_level.txt
kiro_process_manager-1.1.2.dist-info/RECORD
