Metadata-Version: 2.4
Name: kiro-process-manager
Version: 1.1.2
Summary: 非阻塞后台进程管理工具，解决 Kiro IDE 中服务启动阻塞问题
Home-page: https://github.com/Kevin589981/process-manager-tool
Author: Kiro Process Manager Contributors
Author-email: Kiro Process Manager Contributors <kevin3627713@gmail.com>
License-Expression: MIT
Project-URL: Homepage, https://github.com/Kevin589981/process-manager-tool
Project-URL: Repository, https://github.com/Kevin589981/process-manager-tool
Project-URL: Issues, https://github.com/Kevin589981/process-manager-tool/issues
Keywords: kiro,ide,process,manager,background,service,uvicorn,fastapi
Classifier: Development Status :: 4 - Beta
Classifier: Intended Audience :: Developers
Classifier: Programming Language :: Python :: 3
Classifier: Programming Language :: Python :: 3.7
Classifier: Programming Language :: Python :: 3.8
Classifier: Programming Language :: Python :: 3.9
Classifier: Programming Language :: Python :: 3.10
Classifier: Programming Language :: Python :: 3.11
Classifier: Programming Language :: Python :: 3.12
Classifier: Topic :: Software Development :: Libraries
Classifier: Topic :: Software Development :: Libraries :: Python Modules
Classifier: Topic :: System :: Systems Administration
Classifier: Operating System :: OS Independent
Classifier: Environment :: Console
Requires-Python: >=3.7
License-File: LICENSE
Dynamic: author
Dynamic: home-page
Dynamic: license-file
Dynamic: requires-python
